google/cloud/ndb/__init__.py
google/cloud/ndb/_batch.py
google/cloud/ndb/_cache.py
google/cloud/ndb/_datastore_api.py
google/cloud/ndb/_datastore_query.py
google/cloud/ndb/_datastore_types.py
google/cloud/ndb/_eventloop.py
google/cloud/ndb/_gql.py
google/cloud/ndb/_legacy_entity_pb.py
google/cloud/ndb/_legacy_protocol_buffer.py
google/cloud/ndb/_options.py
google/cloud/ndb/_remote.py
google/cloud/ndb/_retry.py
google/cloud/ndb/_transaction.py
google/cloud/ndb/blobstore.py
google/cloud/ndb/client.py
google/cloud/ndb/context.py
google/cloud/ndb/django_middleware.py
google/cloud/ndb/exceptions.py
google/cloud/ndb/global_cache.py
google/cloud/ndb/key.py
google/cloud/ndb/metadata.py
google/cloud/ndb/model.py
google/cloud/ndb/msgprop.py
google/cloud/ndb/polymodel.py
google/cloud/ndb/query.py
google/cloud/ndb/stats.py
google/cloud/ndb/tasklets.py
google/cloud/ndb/utils.py
google/cloud/ndb/version.py
google_cloud_ndb-2.4.0.dist-info/licenses/AUTHORS
google_cloud_ndb-2.4.0.dist-info/licenses/LICENSE
google_cloud_ndb-2.4.0.dist-info/METADATA
google_cloud_ndb-2.4.0.dist-info/WHEEL
google_cloud_ndb-2.4.0.dist-info/top_level.txt
google_cloud_ndb-2.4.0.dist-info/RECORD
