Metadata-Version: 2.4
Name: google-cloud-ndb
Version: 2.4.0
Summary: NDB library for Google Cloud Datastore
Home-page: https://github.com/googleapis/python-ndb
Author: Google LLC
Author-email: googleapis-packages@google.com
License: Apache 2.0
Project-URL: Documentation, https://googleapis.dev/python/python-ndb/latest
Project-URL: Issue Tracker, https://github.com/googleapis/python-ndb/issues
Platform: Posix; MacOS X; Windows
Classifier: Development Status :: 5 - Production/Stable
Classifier: Intended Audience :: Developers
Classifier: License :: OSI Approved :: Apache Software License
Classifier: Programming Language :: Python
Classifier: Programming Language :: Python :: 3
Classifier: Programming Language :: Python :: 3.7
Classifier: Programming Language :: Python :: 3.8
Classifier: Programming Language :: Python :: 3.9
Classifier: Programming Language :: Python :: 3.10
Classifier: Programming Language :: Python :: 3.11
Classifier: Programming Language :: Python :: 3.12
Classifier: Programming Language :: Python :: 3.13
Classifier: Programming Language :: Python :: 3.14
Classifier: Operating System :: OS Independent
Classifier: Topic :: Internet
Requires-Python: >=3.7
License-File: LICENSE
License-File: AUTHORS
Requires-Dist: google-api-core[grpc]!=2.0.*,!=2.1.*,!=2.10.*,!=2.2.*,!=2.3.*,!=2.4.*,!=2.5.*,!=2.6.*,!=2.7.*,!=2.8.*,!=2.9.*,<3.0.0,>=1.34.0
Requires-Dist: google-cloud-datastore!=2.20.2,<3.0.0,>=2.16.0
Requires-Dist: protobuf!=4.21.0,!=4.21.1,!=4.21.2,!=4.21.3,!=4.21.4,!=4.21.5,<7.0.0,>=3.20.2
Requires-Dist: pymemcache<5.0.0,>=2.1.0
Requires-Dist: pytz>=2018.3
Requires-Dist: redis<7.0.0,>=3.0.0
Dynamic: author
Dynamic: author-email
Dynamic: classifier
Dynamic: description
Dynamic: description-content-type
Dynamic: home-page
Dynamic: license
Dynamic: license-file
Dynamic: platform
Dynamic: project-url
Dynamic: requires-dist
Dynamic: requires-python
Dynamic: summary
